setup.py
Probability_Distribution.egg-info/PKG-INFO
Probability_Distribution.egg-info/SOURCES.txt
Probability_Distribution.egg-info/dependency_links.txt
Probability_Distribution.egg-info/not-zip-safe
Probability_Distribution.egg-info/top_level.txt
distributions/Binomialdistribution.py
distributions/Gaussiandistribution.py
distributions/Generaldistribution.py
distributions/__init__.py