Metadata-Version: 1.0
Name: Probability-Distribution
Version: 0.1
Summary: Gaussian and Binomial distributions
Home-page: UNKNOWN
Author: Omar Essam
Author-email: omar12694@gmail.com
License: UNKNOWN
Platform: UNKNOWN
